{
  "video": {
    "id": "4jC67AVcbms",
    "title": "BASTION AND FROM DUST (Zero Punctuation)",
    "url": "https://youtu.be/4jC67AVcbms",
    "duration": 317,
    "playlistId": "unknown",
    "playlistTitle": "Zero Punctuation"
  },
  "captions": [
    {
      "text": "I always feel around this time of year that playing nothing but triple-A mainstream games",
      "offset": 0,
      "duration": 19.14
    },
    {
      "text": "is like eating McDonald's for every meal of the day and my mental equivalent of my",
      "offset": 19.14,
      "duration": 2.8599999999999994
    },
    {
      "text": "intestinal tract is about ready to slither up my throat, pop out my mouth and go look",
      "offset": 22,
      "duration": 3.3200000000000003
    },
    {
      "text": "for food on its own.",
      "offset": 25.32,
      "duration": 1.1000000000000014
    },
    {
      "text": "So enough with these iron sight examination simulators, I'm going where the worlds are",
      "offset": 26.42,
      "duration": 3.1599999999999966
    },
    {
      "text": "The bleak and the heads are large for my third XBLA double bill.",
      "offset": 29.58,
      "duration": 3.1000000000000014
    },
    {
      "text": "And with characteristic convenience, the Casplar has recently chundered up two games that both",
      "offset": 32.68,
      "duration": 3.479999999999997
    },
    {
      "text": "approach the theme of world-building from vastly different directions.",
      "offset": 36.16,
      "duration": 3.1200000000000045
    },
    {
      "text": "Perhaps this speaks to some larger trend within society today, a prevailing desire on the",
      "offset": 39.28,
      "duration": 3.1400000000000006
    },
    {
      "text": "part of indie developers to recreate the entire world into one where you can charge more than",
      "offset": 42.42,
      "duration": 3.1799999999999997
    },
    {
      "text": "fifteen bucks for your game design degree coursework.",
      "offset": 45.6,
      "duration": 2.1599999999999966
    },
    {
      "text": "Well now I am reading too much into things so let's start with Sebastian.",
      "offset": 47.76,
      "duration": 2.8800000000000026
    },
    {
      "text": "Sorry, The Bastion.",
      "offset": 50.64,
      "duration": 1
    },
    {
      "text": "Sebastian is a 2D isometric hacky-slashy but also long-rangey fighty-clustery mobby thing.",
      "offset": 51.64,
      "duration": 4.439999999999998
    },
    {
      "text": "You play a dude, perhaps, named Sebastian, who wakes up one morning to find that the",
      "offset": 56.08,
      "duration": 2.780000000000001
    },
    {
      "text": "The 10 or 15 square feet of floor on which you went to sleep the previous night is now floating, apparently unsupported, in thin air.",
      "offset": 58.86,
      "duration": 5
    },
    {
      "text": "Soon we learn that an ominously named calamity has blown up most of the world, the kind of blown up that grants the debris the ability to fly and makes more debris materialize under your feet when you walk off it.",
      "offset": 63.86,
      "duration": 8.200000000000003
    },
    {
      "text": "Man that doesn sound like a calamity at all That sounds pretty fucking rad Okay it killed the vast majority of the population but still it paradise for an anthropophobic aeronautics engineer Your task is to assist in the construction of a floating stronghold from which a new society could be formed by going to missions and murdering everything that moves",
      "offset": 72.06,
      "duration": 13.765169999999998
    },
    {
      "text": "As well as quite a few things that don't move, too.",
      "offset": 85.82517,
      "duration": 1.8599999999999994
    },
    {
      "text": "The environments are absolutely littered with clashing terrain, enemies, and destructible",
      "offset": 87.68517,
      "duration": 2.980010000000007
    },
    {
      "text": "furniture, and together with the isometric viewpoint which is to confusing perspective",
      "offset": 90.66518,
      "duration": 2.8399900000000002
    },
    {
      "text": "what the Thames was to cholera, it all looks a bit of a mess, which is, funnily enough,",
      "offset": 93.50517,
      "duration": 3.1600099999999998
    },
    {
      "text": "something else people say about the Thames.",
      "offset": 96.66518,
      "duration": 1.5999949999999927
    },
    {
      "text": "Combat is quite efficient, mind, creating the right warm jolt of self-satisfaction that",
      "offset": 98.265175,
      "duration": 2.9599989999999963
    },
    {
      "text": "comes from correctly dodging, countering, or snorting coke.",
      "offset": 101.225174,
      "duration": 2.3000060000000104
    },
    {
      "text": "But there are probably too many weapons and the usual problem with an upgrade system that you become fucking Thor by the end of it,",
      "offset": 103.52518,
      "duration": 4.719989999999996
    },
    {
      "text": "who annihilates every possible challenge with a single shift of his tightened buttocks.",
      "offset": 108.24517,
      "duration": 3.2800100000000043
    },
    {
      "text": "But where Bastion shines is in the story.",
      "offset": 111.52518,
      "duration": 2
    },
    {
      "text": "People ask me,",
      "offset": 113.52518,
      "duration": 0.5599950000000007
    },
    {
      "text": "Yartzer, you say you like story and gameplay that blend seamlessly,",
      "offset": 114.085175,
      "duration": 2.639998999999989
    },
    {
      "text": "but can you give an example without mentioning Silent Hill 2 or Half-Life like you always bloody do?",
      "offset": 116.725174,
      "duration": 4.119996
    },
    {
      "text": "Alright then, now there's the Bastion as well.",
      "offset": 120.84517,
      "duration": 1.7999999999999972
    },
    {
      "text": "Without interrupting gameplay, much,",
      "offset": 122.64517,
      "duration": 1.6800000000000068
    },
    {
      "text": "the story is told by an ongoing and disturbingly sexy narration",
      "offset": 124.32517,
      "duration": 2.9200000000000017
    },
    {
      "text": "by someone who appears to have replaced his lungs with two chocolate profiteroles.",
      "offset": 127.24517,
      "duration": 3.039999999999992
    },
    {
      "text": "From a starting position of knowing something between bugger and all,",
      "offset": 130.28517,
      "duration": 2.7600000000000193
    },
    {
      "text": "We gradually piece together the storied history of the world before it got reduced to cornflakes,",
      "offset": 133.04517,
      "duration": 3.6799999999999784
    },
    {
      "text": "all while remaining focused on a core group of interesting characters the story retains",
      "offset": 136.72517,
      "duration": 3.2600000000000193
    },
    {
      "text": "emotional weight, and events are driven by the actions of the protagonist.",
      "offset": 139.98517,
      "duration": 3.219999999999999
    },
    {
      "text": "It's everything a game's story should be.",
      "offset": 143.20517,
      "duration": 1.8200099999999964
    },
    {
      "text": "That said, if you are going to have two endings based on the last decision we make in the",
      "offset": 145.02518,
      "duration": 2.8599800000000073
    },
    {
      "text": "game, for fuck's sake put a save point before it because I've now got the entire last",
      "offset": 147.88516,
      "duration": 3.540009999999995
    },
    {
      "text": "mission of the game stuck in my head like it Oh What A Night by the Four Seasons Anyway let leave you trying to remember how that song goes and move on to this week second game From Dust a new game from Eric Chahi And those of you who weren testicle spelunkers in the early 90s may remember him as the developer",
      "offset": 151.42517,
      "duration": 12.325179999999989
    },
    {
      "text": "behind the groundbreaking and atmospheric Another World.",
      "offset": 163.75035,
      "duration": 2.5600000000000023
    },
    {
      "text": "That's out of this world if your country is dumb.",
      "offset": 166.31035,
      "duration": 1.9199999999999875
    },
    {
      "text": "But let's stop upsetting the children with references to the pre-Lady Gaga world.",
      "offset": 168.23035,
      "duration": 3.3600000000000136
    },
    {
      "text": "From Dust is a sort of mythic creation story about a tribe of primitive people overcoming",
      "offset": 171.59035,
      "duration": 3.280000000000001
    },
    {
      "text": "their crippling shyness to colonise a series of lands.",
      "offset": 174.87035,
      "duration": 2.6199900000000014
    },
    {
      "text": "And just to show how far Eric's come in twenty years, the main character is not a",
      "offset": 177.49034,
      "duration": 3.079999999999984
    },
    {
      "text": "Not a ginger dork in a t-shirt, but a magic glowing snake with the power to move terrain around on a terrifying scale.",
      "offset": 180.57034,
      "duration": 5
    },
    {
      "text": "You have to help the little masked men found a set number of villages and fend off environmental hazards like floods and lava,",
      "offset": 185.57034,
      "duration": 5
    },
    {
      "text": "because magical glowing snakes lack the communication skills to suggest their masters build a village somewhere other than an active volcano mouth, you stupid gibbering tits.",
      "offset": 190.57034,
      "duration": 7
    },
    {
      "text": "At first glance, From Dust strongly evokes both Populous and Black and White as if it was developed by some parallel universe version of Peter Molyneux who didn't start taking loony pills around the early 2000s.",
      "offset": 197.57034,
      "duration": 8
    },
    {
      "text": "Subtitles by the Amara community This really misses the ability to make specific men stand on specific spots when the elements are closing in but it hard to feel guilty about losing anyone when they didn think to sprint As seen in the video half of the",
      "offset": 205.57034,
      "duration": 43.14518000000001
    },
    {
      "text": "That's always the problem with gameplay mechanics and this kind of procedural generation stuff,",
      "offset": 248.71552,
      "duration": 3.279989999999998
    },
    {
      "text": "there tends to be a fine line between what it'll accept and what it'll throw back in your face like",
      "offset": 251.99551,
      "duration": 3.519990000000007
    },
    {
      "text": "a bowl of mashed apple. The game refuses to let you build a village in a recently drained area,",
      "offset": 255.5155,
      "duration": 3.7600000000000193
    },
    {
      "text": "if so much as a spoonful of moisture remains anywhere within a 50 foot radius, but once it",
      "offset": 259.2755,
      "duration": 3.7600199999999973
    },
    {
      "text": "is built you can practically build a waterslide park and no one seems to care, as long as you",
      "offset": 263.03552,
      "duration": 3.3599800000000073
    },
    {
      "text": "don't wash all the laundry away. On the whole though, I had fun with From Dust and if you get",
      "offset": 266.3955,
      "duration": 3.67999999999995
    },
    {
      "text": "through to the very end you unlock a sandbox map that lets you build whatever, but after finishing",
      "offset": 270.0755,
      "duration": 3.4399999999999977
    },
    {
      "text": "my inevitable spewing lava penis I realised the game really did need some challenge to make it",
      "offset": 273.5155,
      "duration": 4.160000000000025
    },
    {
      "text": "Interesting. And giving me the power to spawn a tsunami but not tell me which button it is only really works once, game.",
      "offset": 277.6755,
      "duration": 5.439999999999998
    },
    {
      "text": "Of the two games herein discussed, I think I prefer Sebastian. He feels a bit richer and doesn't spend so much time rolling around in the dirt.",
      "offset": 283.1155,
      "duration": 5.920020000000022
    },
    {
      "text": "But then again, we'll never find out if Sebastian gets better if you get bored and drop 500 tons of molten stone on someone's conservatory.",
      "offset": 289.03552,
      "duration": 6.079979999999978
    },
    {
      "text": "Thanks for watching!",
      "offset": 307.6755,
      "duration": 5
    }
  ],
  "fetchedAt": "2025-12-14T11:39:10.264Z"
}