{
  "video": {
    "id": "7EpzwuZOvKY",
    "title": "ON THE ESCAPIST (Zero Punctuation)",
    "url": "https://youtu.be/7EpzwuZOvKY",
    "duration": 54,
    "playlistId": "PLAbMhAYRuCUhawCEV2oXZGrienoKTN16X",
    "playlistTitle": "Zero Punctuation"
  },
  "captions": [
    {
      "text": "There's a series of unlockable bonus cards that make it easier to murder tons of dudes.",
      "offset": 0,
      "duration": 5.04
    },
    {
      "text": "There's a soul collecting gameplay element that results in a new and interesting way",
      "offset": 5.04,
      "duration": 2.76
    },
    {
      "text": "to murder tons of dudes.",
      "offset": 7.8,
      "duration": 1.0000000000000009
    },
    {
      "text": "Okay, so maybe it is nothing but murdering tons of dudes.",
      "offset": 8.8,
      "duration": 2.4399999999999995
    },
    {
      "text": "Engineering a scenario in which Mario can brutally beat the stupid out of Princess Peach",
      "offset": 11.24,
      "duration": 3.4800000000000004
    },
    {
      "text": "while the crowd screams for blood is very satisfying.",
      "offset": 14.72,
      "duration": 2.1599999999999984
    },
    {
      "text": "Personally, if it comes down to a fight between two guys who make a living jumping on people,",
      "offset": 16.88,
      "duration": 3.1999999999999993
    },
    {
      "text": "then my money's on the one with spikes growing out of his flesh.",
      "offset": 20.08,
      "duration": 2.4800000000000004
    },
    {
      "text": "Also, you have one second to name any game in which weapon degradation has been a good",
      "offset": 22.56,
      "duration": 3.120000000000001
    },
    {
      "text": "idea.",
      "offset": 25.68,
      "duration": 1
    },
    {
      "text": "I could mention the hugely satisfying penis extension gun that pins baddies to walls with",
      "offset": 26.68,
      "duration": 3.240000000000002
    },
    {
      "text": "I wish I could make something like that up. It shoots shurikens and lightning. It could",
      "offset": 29.92,
      "duration": 3.8399999999999963
    },
    {
      "text": "only be more awesome if it had tits and was on fire. I thank Christ for the automatic",
      "offset": 33.76,
      "duration": 3.8000000000000043
    },
    {
      "text": "lock-on in the firefight because all the enemies are indistinct dark blobs in an indistinct",
      "offset": 37.56,
      "duration": 3.479999999999997
    },
    {
      "text": "dark blob factory.",
      "offset": 41.04,
      "duration": 0.9399999999999977
    }
  ],
  "fetchedAt": "2025-12-14T11:28:42.127Z",
  "publishedAt": "2008-09-23"
}