{
  "video": {
    "id": "dZ32bP12DoQ",
    "title": "INVERSION (Zero Punctuation)",
    "url": "https://youtu.be/dZ32bP12DoQ",
    "duration": 349,
    "playlistId": "PLAbMhAYRuCUhawCEV2oXZGrienoKTN16X",
    "playlistTitle": "Zero Punctuation"
  },
  "captions": [
    {
      "text": "You know, thanks to Specops the line, the world is a slightly happier if rather bleakly",
      "offset": 0,
      "duration": 19.4
    },
    {
      "text": "confrontational place, but at the same time it's made my job a little more complicated.",
      "offset": 19.4,
      "duration": 3.580000000000002
    },
    {
      "text": "Its intense and well-structured story, in the trappings of a load of generic realistic",
      "offset": 22.98,
      "duration": 3.099999999999998
    },
    {
      "text": "shooter xenophobia fun, proves that you shouldn't judge a book by its cover, which is a shame",
      "offset": 26.08,
      "duration": 3.740000000000002
    },
    {
      "text": "I'm gonna judge the fuck out of Inversion by its cover.",
      "offset": 29.82,
      "duration": 29.979999999999997
    },
    {
      "text": "It's cover-based shooting, that is!",
      "offset": 59.8,
      "duration": 2.6799999999999997
    },
    {
      "text": "Another thing that illustrates how AAA games are terrified your soup-like monkey mind will",
      "offset": 62.48,
      "duration": 3.70000000000001
    },
    {
      "text": "be distracted from their game by the rustling of the leaves on next door's Leylandii is",
      "offset": 66.18,
      "duration": 3.279999999999987
    },
    {
      "text": "the flash-forward, where the action starts by skipping ahead to the very end of the game",
      "offset": 69.46,
      "duration": 3.220000000000013
    },
    {
      "text": "to reassure us that shit's gone get fucked, and which is fast becoming mandatory for second-rate",
      "offset": 72.68,
      "duration": 4.4199999999999875
    },
    {
      "text": "shooters.",
      "offset": 77.1,
      "duration": 1
    },
    {
      "text": "It's not even like Inversion has a slow start.",
      "offset": 78.1,
      "duration": 1.5
    },
    {
      "text": "A game like Heavy Rain where you spend the first six hours mooching around the house systematically running out of children could have benefited from the briefest of hints that you eventually get to see people tits But Inversion plot starts with about thirty seconds of a bloke working as a cop in a glittering utopian city before the very earth cracks asunder and the armies of Lord Humongous burst",
      "offset": 79.6,
      "duration": 16.43467000000001
    },
    {
      "text": "in and start killing everyone. That's thirty seconds of things being perfectly fine before",
      "offset": 96.03467,
      "duration": 3.5799999999999983
    },
    {
      "text": "shit rockets fanwards that apparently haunted the developers with visions of players switching",
      "offset": 99.61467,
      "duration": 4
    },
    {
      "text": "off twenty-nine seconds in, going, man I ain't down for no things being perfectly fine simulator,",
      "offset": 103.61467,
      "duration": 4.599999999999994
    },
    {
      "text": "Let's go flick staples at the cat.",
      "offset": 108.21467,
      "duration": 1.8200000000000074
    },
    {
      "text": "Our aforementioned cop bloke hero is named either Davis Russell or Russell Davis, I honestly",
      "offset": 110.03467,
      "duration": 3.9199959999999976
    },
    {
      "text": "couldn't figure out which, and he resembles the head of a Ken doll stuck on the body of",
      "offset": 113.954666,
      "duration": 3.180008000000001
    },
    {
      "text": "a WrestleMania action figure.",
      "offset": 117.134674,
      "duration": 1.5
    },
    {
      "text": "His daughter gets captured by the invaders and I guess she must have been keeping his",
      "offset": 118.634674,
      "duration": 2.6399959999999965
    },
    {
      "text": "insulin in her lunchbox or something because the desire to get her back is literally his",
      "offset": 121.27467,
      "duration": 3.4200000000000017
    },
    {
      "text": "only motivation.",
      "offset": 124.69467,
      "duration": 1
    },
    {
      "text": "There's a point where fatherly devotion gets a bit weird, you know?",
      "offset": 125.69467,
      "duration": 2.9000000000000057
    },
    {
      "text": "I mean, the world's being invaded, you could always stay home and make another one.",
      "offset": 128.59467,
      "duration": 3.3399900000000002
    },
    {
      "text": "You're not gonna be able to do that if the enemy shoots your bollocks off while you're",
      "offset": 131.93466,
      "duration": 2.540009999999995
    },
    {
      "text": "assaulting their headquarters looking for her.",
      "offset": 134.47467,
      "duration": 1.9799999999999898
    },
    {
      "text": "So basically this is Gears of War with the Dom's Wife subplot upgraded into the protagonist's",
      "offset": 136.45467,
      "duration": 3.9399999999999977
    },
    {
      "text": "sole character trait.",
      "offset": 140.39467,
      "duration": 1.2199999999999989
    },
    {
      "text": "The levels do the same Gears of War thing where they go, hey, look at this amazing skybox",
      "offset": 141.61467,
      "duration": 3.5
    },
    {
      "text": "we spent months on, bet you'd like to be playing around in that, wouldn't you?",
      "offset": 145.11467,
      "duration": 2.8799900000000207
    },
    {
      "text": "Now go crouch next to a wall and growl at things like a trapped stoat.",
      "offset": 147.99466,
      "duration": 3.3600199999999916
    },
    {
      "text": "The characters even stand like they do in Gears of War, with legs apart and an alert",
      "offset": 151.35468,
      "duration": 3.219999999999999
    },
    {
      "text": "smugness to their posture like they're bracing themselves for the moment their six-foot cocks",
      "offset": 154.57468,
      "duration": 3.2599899999999877
    },
    {
      "text": "uncoil and thump to the floor.",
      "offset": 157.83467,
      "duration": 1.7400100000000123
    },
    {
      "text": "Yahtzee, you tired old late-twenties codger.",
      "offset": 159.57468,
      "duration": 2.519990000000007
    },
    {
      "text": "I hear you cry.",
      "offset": 162.09467,
      "duration": 1.1599999999999966
    },
    {
      "text": "Your opinions on swaggering meathead cover shooters are well documented.",
      "offset": 163.25467,
      "duration": 2.859999999999985
    },
    {
      "text": "Why you even pick this game up unless you had severe congestion and thought a few good sneers would fix it Well you know me I a sucker for innovation and Cadbury Cream Eggs one of which Inversion purported to possess The game employs a variety of gravity mechanics for example both the player and the enemy can cancel gravity in small",
      "offset": 166.11467,
      "duration": 13.754670000000004
    },
    {
      "text": "areas to make enemies appear out of cover, a service that's questionably useful since",
      "offset": 179.86934,
      "duration": 3.5800000000000125
    },
    {
      "text": "the standard mode of behaviour for enemies in any cover-based shooter is to pop up and",
      "offset": 183.44934,
      "duration": 3.3200099999999964
    },
    {
      "text": "down like little wooden ducks anyway. You can also launch physics objects at enemies",
      "offset": 186.76935,
      "duration": 3.519990000000007
    },
    {
      "text": "at high speed, almost as if you can employ your gravity powers as a gun. Although for",
      "offset": 190.28934,
      "duration": 4.139999999999986
    },
    {
      "text": "some reason you can only pick up and fire physics objects that have been in a zero gravity",
      "offset": 194.42934,
      "duration": 3.1599999999999966
    },
    {
      "text": "Okay, firstly we're taking ideas from eight years ago, and secondly we're doing it vastly worse.",
      "offset": 197.58934,
      "duration": 5.200000000000017
    },
    {
      "text": "A mechanic in a shooter that's markedly less convenient than just pointing and shooting until",
      "offset": 202.78934,
      "duration": 4.079999999999984
    },
    {
      "text": "the man's fall down is the very definition of a gimmick, so where are those Cadbury's",
      "offset": 206.86934,
      "duration": 4.0800000000000125
    },
    {
      "text": "creme eggs you promised me, Inversion? There's nothing wrong with cover shooting. Spec Ops,",
      "offset": 210.94934,
      "duration": 3.759999999999991
    },
    {
      "text": "Max Payne, that new Deus Ex with the sunglasses twat, all of these illustrate that cover shooting",
      "offset": 214.70934,
      "duration": 3.9199900000000127
    },
    {
      "text": "is fine if it serves the game, if it's the glue connecting the actually interesting bits of the",
      "offset": 218.62933,
      "duration": 3.6800099999999816
    },
    {
      "text": "model airplane. But when the interesting bits exist only to serve the cover shooting, then",
      "offset": 222.30934,
      "duration": 3.6799900000000036
    },
    {
      "text": "I'm glad you were never given a green lantern ring.",
      "offset": 225.98933,
      "duration": 13.820009999999996
    },
    {
      "text": "You'd probably just use it to conjure a magical green credit card to pay for a second-hand",
      "offset": 239.80934,
      "duration": 3.4399899999999946
    },
    {
      "text": "spud gun.",
      "offset": 243.24933,
      "duration": 1
    },
    {
      "text": "Couldn't we use our gravity powers to, you know, fly?",
      "offset": 244.24933,
      "duration": 3.160000000000025
    },
    {
      "text": "Well it's funny I should mention that.",
      "offset": 247.40933,
      "duration": 1.1000099999999975
    },
    {
      "text": "There are fenced-off zero-gravity bits, but all you're allowed to do is move back and",
      "offset": 248.50934,
      "duration": 3
    },
    {
      "text": "forth between, you guessed it, COVER.",
      "offset": 251.50934,
      "duration": 2.5999999999999943
    },
    {
      "text": "When you not on cover all you can do is violently fart every ten seconds or so to nudge yourself a foot or two closer to cover At one point I was out of cover near the level exit and tried to fart my way inside but bounced off one of the cover shooter genre beloved invisible walls because they would only let",
      "offset": 254.10934,
      "duration": 12.834689999999995
    },
    {
      "text": "me in if I was in the cover next to it and pressed the contextual exit level button.",
      "offset": 266.94403,
      "duration": 3.880010000000027
    },
    {
      "text": "Be ye video game inversion or be ye checklist.",
      "offset": 270.82404,
      "duration": 3.3399900000000002
    },
    {
      "text": "Oh yes, and sometimes there are predetermined gates that make gravity shift 90 degrees so",
      "offset": 274.16403,
      "duration": 3.88000999999997
    },
    {
      "text": "you can fight enemies on the sides of buildings hiding behind signs and ventilation shafts,",
      "offset": 278.04404,
      "duration": 3.459990000000005
    },
    {
      "text": "but it's just another way of inorganically connecting one linear shooting arena to the",
      "offset": 281.50403,
      "duration": 3.3200100000000248
    },
    {
      "text": "next.",
      "offset": 284.82404,
      "duration": 1
    },
    {
      "text": "They have a half-arsed plot full of boorish assholes and boss fights repeated ad nauseam",
      "offset": 285.82404,
      "duration": 3.599959999999953
    },
    {
      "text": "that squanders what potential it has in the name of ticking the same triple-A shooter boxes",
      "offset": 289.424,
      "duration": 3.240030000000047
    },
    {
      "text": "as always, and I'm not sure why they called it Inversion when you only get to walk on",
      "offset": 292.66403,
      "duration": 3.1600099999999998
    },
    {
      "text": "the ceiling, like, once.",
      "offset": 295.82404,
      "duration": 1.2999799999999482
    },
    {
      "text": "A more appropriate title might have suited, like Another Meaningless Distraction on the",
      "offset": 297.12402,
      "duration": 3.299980000000005
    },
    {
      "text": "Inexorable Path to the Grave.",
      "offset": 300.424,
      "duration": 1.5200300000000198
    },
    {
      "text": "Although there is one bit in the opening narration where Russell Davis Russell drops the title",
      "offset": 301.94403,
      "duration": 3.6399700000000053
    },
    {
      "text": "word while waffling on about how much things have changed lately.",
      "offset": 305.584,
      "duration": 3.2000299999999697
    },
    {
      "text": "Oh, okay, glad we cleared that up.",
      "offset": 308.78403,
      "duration": 2.11999000000003
    },
    {
      "text": "So what the title's supposed to be saying is that this is the story all about how my",
      "offset": 310.90402,
      "duration": 2.959979999999973
    },
    {
      "text": "life got flipped turned upside down.",
      "offset": 313.864,
      "duration": 1.920029999999997
    },
    {
      "text": "The Escapist Expo is still in September and you should still totally come, but also in October I've got a second novel coming out.",
      "offset": 315.82404,
      "duration": 25.199979999999982
    },
    {
      "text": "It's called JAM and you can pre-order it from Amazon and TFAW.com.",
      "offset": 341.02402,
      "duration": 4.640010000000018
    },
    {
      "text": "It's about an apocalypse with jam in it.",
      "offset": 345.66403,
      "duration": 2.7199999999999704
    }
  ],
  "fetchedAt": "2025-12-14T11:36:26.304Z",
  "publishedAt": "2012-10-25"
}