{
  "video": {
    "id": "eP-OLKkbiBc",
    "title": "CALL OF DUTY: BLACK OPS (Zero Punctuation)",
    "url": "https://youtu.be/eP-OLKkbiBc",
    "duration": 312,
    "playlistId": "unknown",
    "playlistTitle": "Zero Punctuation"
  },
  "captions": [
    {
      "text": "Could somebody please invade America? I know it's not exactly prime real estate and can just about produce corn and shitty TV, but someone really needs to help them blow off some steam.",
      "offset": 0,
      "duration": 23.9
    },
    {
      "text": "It's hard not to look at all these war games about Russia invading America and not be reminded of fanfiction.",
      "offset": 23.9,
      "duration": 4.220000000000002
    },
    {
      "text": "America is a fat teenage virgin lying on her front on her bed, staring up at her Edward and Bella poster while crossing and uncrossing her ankles and dreamily writing creepy stories",
      "offset": 28.12,
      "duration": 7.800000000000001
    },
    {
      "text": "about having filthy monkey sex with the quiet Eastern European boy down the road.",
      "offset": 35.92,
      "duration": 3.3799999999999955
    },
    {
      "text": "And the child psychologist hired by her concerned parents gives the following advice,",
      "offset": 39.3,
      "duration": 3.3200000000000003
    },
    {
      "text": "what this girl needs is a good hard dicking.",
      "offset": 42.62,
      "duration": 2.3599999999999994
    },
    {
      "text": "So come on, Russia, take the hint. World War III, let's do it.",
      "offset": 44.98,
      "duration": 2.720000000000006
    },
    {
      "text": "Yeah, lots of people will die, but it's not like the human race couldn't use a bit of a pruning now and then.",
      "offset": 47.7,
      "duration": 3.6400000000000006
    },
    {
      "text": "What about you, China? You've got loads of people to spare, you selfish bastards.",
      "offset": 51.34,
      "duration": 3.219999999999999
    },
    {
      "text": "I say, ram a few of them up America's rancid, hairy funhole and maybe she can remember how",
      "offset": 54.56,
      "duration": 3.5
    },
    {
      "text": "to act like a grown-up and come like a howler monkey.",
      "offset": 58.06,
      "duration": 2.739999999999995
    },
    {
      "text": "Anyway, here's America's latest virginal howler monkey sex fantasy, Call of Duty Black",
      "offset": 60.8,
      "duration": 3.5400000000000063
    },
    {
      "text": "Ops, another opportunity for the Call of Duty franchise to wave military hardware in our",
      "offset": 64.34,
      "duration": 3.219999999999999
    },
    {
      "text": "faces and go FWARAY, this time with a bit of a heavy Mancurian candidate influence,",
      "offset": 67.56,
      "duration": 4.079999999999998
    },
    {
      "text": "but don worry it not so heavy that it gets in the way of all the shooting foreigners You mostly play Aryan Superman Alex Mason Not to be confused with Alec Mason the protagonist of Red Faction Guerrilla Are there so few white Anglo tough guy hero names in the world that you have to start recycling I can think of loads off the top of my head Gabriel Stone Dirk Action John Fist Anyway Blake Shrapnel has been strapped to a chair and is being tortured for information by shadowy figures who want to know the truth behind a string of mysterious numbers that like the Inspector Gadget theme tune he just can get out of his head This sends him into various flashbacks of past missions to form a framing device for the action Events rattle undisciplined back and forth through time",
      "offset": 71.64,
      "duration": 31.239739999999998
    },
    {
      "text": "From the Bay of Pigs invasion to the Vietnam War to an interview with JFK being played by someone doing an absurd comedy JFK impression.",
      "offset": 102.87974,
      "duration": 5.700000000000003
    },
    {
      "text": "And there are many moments when I just want to yell timeout and demand someone explain what the fuck's going on before another thing explodes.",
      "offset": 108.57974,
      "duration": 5.799999999999997
    },
    {
      "text": "Because the thing about all the Call of Duty games I've played lately is that they all seem to be hooked up to IV drips full of pop rocks.",
      "offset": 114.37974,
      "duration": 4.6000000000000085
    },
    {
      "text": "Black Ops just can't calm the fuck down. If five seconds ever pass without a gunshot or an explosion, then it's probably because you just passed out from an epileptic fit.",
      "offset": 118.97974,
      "duration": 6.5
    },
    {
      "text": "The game's like a nagging spouse slapping you around the back of the head every five seconds.",
      "offset": 125.47974,
      "duration": 2.999999999999986
    },
    {
      "text": "Go there, keep running, take cover, not there, you're getting shot, there, shoot that guy, not him, he's on your side, can't you tell he's wearing a slightly different hat?",
      "offset": 128.47974,
      "duration": 5.8999900000000025
    },
    {
      "text": "Quick, pick up that grenade and throw it back, I don't know, over there somewhere, oh, there, see? If you'd thrown it sooner, that wouldn't have happened, you stupid cunt.",
      "offset": 134.37973,
      "duration": 5.659999999999997
    },
    {
      "text": "You only get a break on the loading screens, which will generally helpfully remind you that grenades explode, and you should probably avoid getting exploded in future.",
      "offset": 140.03973,
      "duration": 5.880009999999999
    },
    {
      "text": "I know the sorts of attention spans you working with can stick with a 15 shampoo advert unless you flash some titties halfway through Treyarch but there is such a thing as juxtaposition If the action never lets up we got no point of comparison and it too overwhelming to focus on I played through a lot of this game in a trance Writing this review I had to think really hard to recall where the first mission took",
      "offset": 145.91974,
      "duration": 15.879730000000023
    },
    {
      "text": "place and I only know it was Cuba because I remembered Fidel Castro showing up twirling",
      "offset": 161.79947,
      "duration": 3.3799999999999955
    },
    {
      "text": "his moustache like Snidely Whiplash.",
      "offset": 165.17947,
      "duration": 1.9199999999999875
    },
    {
      "text": "So what does the term Black Ops evoke in your mind?",
      "offset": 167.09947,
      "duration": 2.1600099999999998
    },
    {
      "text": "Espionage, darkened meetings in smoky car parks, exchanging a package with another spy",
      "offset": 169.25948,
      "duration": 3.3600000000000136
    },
    {
      "text": "in a public place by awkwardly pretending to make out, and most importantly, deniability.",
      "offset": 172.61948,
      "duration": 4.219999999999999
    },
    {
      "text": "It occurs to me that the American government would have considerable difficulty denying",
      "offset": 176.83948,
      "duration": 2.6399999999999864
    },
    {
      "text": "I'm not saying the kinds of things that go on in Black Ops.",
      "offset": 179.47948,
      "duration": 1.8999900000000025
    },
    {
      "text": "What's that, Vladimir?",
      "offset": 181.37947,
      "duration": 1
    },
    {
      "text": "No, no, that fleets of American aircraft carriers were just in that particular bit of ocean for",
      "offset": 182.37947,
      "duration": 2.8800099999999986
    },
    {
      "text": "a volleyball tournament and to take some photos for a navy recruitment booklet.",
      "offset": 185.25948,
      "duration": 2.960000000000008
    },
    {
      "text": "No, I can't imagine how one of your battleships in the exact same area could have gotten riddled",
      "offset": 188.21948,
      "duration": 3.4799999999999898
    },
    {
      "text": "with bullets.",
      "offset": 191.69948,
      "duration": 1
    },
    {
      "text": "Well then now I come to think about it, I do remember hearing what could have been minigun",
      "offset": 192.69948,
      "duration": 2.460000000000008
    },
    {
      "text": "fire but at the time I thought it was just someone playing squash very, very enthusiastically.",
      "offset": 195.15948,
      "duration": 4.039999999999992
    },
    {
      "text": "It's disappointing because the title led me to expect a bit of Sneaky Snake stealth gameplay",
      "offset": 199.19948,
      "duration": 3.5200000000000102
    },
    {
      "text": "to break up the testosterone overload but the only thing black about these ops are the",
      "offset": 202.71948,
      "duration": 3.1599899999999934
    },
    {
      "text": "spent shell casings.",
      "offset": 205.87947,
      "duration": 1.2199999999999989
    },
    {
      "text": "Modern Warfare 1 had more stealth than this, and I remind you, that was the game where a nuke goes off in your face.",
      "offset": 207.09947,
      "duration": 4.16001
    },
    {
      "text": "Now that's what I call juxtaposition.",
      "offset": 211.25948,
      "duration": 1.8399900000000002
    },
    {
      "text": "Well, since we're looking for something different, I guess I should mention that the game comes with a zombie minigame,",
      "offset": 213.09947,
      "duration": 3.5
    },
    {
      "text": "because after Call of Duty World at War and the upcoming Red Dead Redemption DLC,",
      "offset": 216.59947,
      "duration": 3.1600099999999998
    },
    {
      "text": "apparently everything now has to be moving towards some kind of zombie singularity, by law.",
      "offset": 219.75948,
      "duration": 3.8399900000000002
    },
    {
      "text": "You fight off waves of the undead, barricading their entry points and opening up more of the map,",
      "offset": 223.59947,
      "duration": 3.5600100000000054
    },
    {
      "text": "while the game constantly nags you to turn on the power without thinking to give any hint on how exactly one does such a thing But I got to admit it kind of fun Play with a friend and then get them to tell you when zombies are breaking in two rooms away Subtitles by the Amara community I don think you find that very tasty",
      "offset": 227.15948,
      "duration": 24.53971999999999
    },
    {
      "text": "Oh bugger my britches that was uncalled for.",
      "offset": 251.6992,
      "duration": 2.0200100000000134
    },
    {
      "text": "Who are the good guys in this game again?",
      "offset": 253.71921,
      "duration": 1.6799900000000036
    },
    {
      "text": "The weird thing is, the character then joins your party after he's done spitting out",
      "offset": 255.3992,
      "duration": 3.1399999999999864
    },
    {
      "text": "Not blood and bits of mouth.",
      "offset": 258.5392,
      "duration": 1.240000000000009
    },
    {
      "text": "That's one working relationship that's off to an awkward start.",
      "offset": 259.7792,
      "duration": 2.079999999999984
    },
    {
      "text": "Tellingly, the game features the Vietnam War and the Bay of Pigs invasion, both for the",
      "offset": 261.8592,
      "duration": 3.3000000000000114
    },
    {
      "text": "longest time avoided by video games because the United States went into them for slightly",
      "offset": 265.1592,
      "duration": 3.100020000000029
    },
    {
      "text": "cunty, unheroic reasons.",
      "offset": 268.25922,
      "duration": 1.739979999999946
    },
    {
      "text": "But I guess Black Ops means we've stopped giving a shit.",
      "offset": 269.9992,
      "duration": 2.180000000000007
    },
    {
      "text": "I guess we're hankering for another decent war so much that we no longer care whether",
      "offset": 272.1792,
      "duration": 3.1200000000000045
    },
    {
      "text": "we're the good guys or not.",
      "offset": 275.2992,
      "duration": 1.1200000000000045
    },
    {
      "text": "So that's why I say let's just do it.",
      "offset": 276.4192,
      "duration": 1.8000000000000114
    },
    {
      "text": "Don't need a reason, just ring up Eastern Europe and say maybe we could do the genocide",
      "offset": 278.2192,
      "duration": 3.1200000000000045
    },
    {
      "text": "thing this time.",
      "offset": 281.3392,
      "duration": 1
    },
    {
      "text": "Then everyone can line up in the Sahara Desert with their latest weapons tech and all just",
      "offset": 282.3392,
      "duration": 3.159999999999968
    },
    {
      "text": "get it out of their system.",
      "offset": 285.4992,
      "duration": 1.3000000000000114
    },
    {
      "text": "Perhaps Switzerland could be persuaded to blow the starting whistle.",
      "offset": 286.7992,
      "duration": 2.6200000000000045
    }
  ],
  "fetchedAt": "2025-12-14T16:51:12.854Z"
}