{
  "video": {
    "id": "fc0u1-Liamk",
    "title": "Overwatch vs Battleborn (Zero Punctuation)",
    "url": "https://youtu.be/fc0u1-Liamk",
    "duration": 345,
    "playlistId": "PLAbMhAYRuCUhawCEV2oXZGrienoKTN16X",
    "playlistTitle": "Zero Punctuation"
  },
  "captions": [
    {
      "text": "Yes, I know what I said a couple weeks back about not doing Battleborn or Overwatch, but",
      "offset": 12230,
      "duration": 3270
    },
    {
      "text": "that was an easier thing to say when I wasn't staring down the dismal tunnel of inevitable",
      "offset": 15500,
      "duration": 3280
    },
    {
      "text": "midyear drought like a gynaecology student cramming for the final exam.",
      "offset": 18780,
      "duration": 3330
    },
    {
      "text": "My argument was, as someone who has never seen the appeal in the standard multiplayer",
      "offset": 22110,
      "duration": 3040
    },
    {
      "text": "game structure of playing the same mission over and over again in the hope of one day",
      "offset": 25150,
      "duration": 2980
    },
    {
      "text": "becoming as skilled as the insufferable passionless cunts that infest the servers, my opinion",
      "offset": 28130,
      "duration": 4120
    },
    {
      "text": "on games that focus on such is akin to Freddy Krueger's opinion on electric hair straighteners.",
      "offset": 32250,
      "duration": 3640
    },
    {
      "text": "But then I thought, hang on, maybe there is value in me playing two different flavours",
      "offset": 35890,
      "duration": 3660
    },
    {
      "text": "of the suddenly inexplicably popular multiplayer hero shooter genre and stating as a confessed",
      "offset": 39550,
      "duration": 4140
    },
    {
      "text": "outsider which one I enjoyed more.",
      "offset": 43690,
      "duration": 1770
    },
    {
      "text": "So, with this brief in mind, I played some Overwatch and some Battleborn.",
      "offset": 45460,
      "duration": 3070
    },
    {
      "text": "And I just know that before this review is over I'm going to slip up and call it Bloodborne,",
      "offset": 48530,
      "duration": 3130
    },
    {
      "text": "even as I'm writing this fucking sentence I'm having to open Steam and determine whether",
      "offset": 51660,
      "duration": 3410
    },
    {
      "text": "or not you spell Battleborn with an E on the end.",
      "offset": 55070,
      "duration": 2169
    },
    {
      "text": "Anyway, the plan was to spend each afternoon this week playing a bit of Battleborn and",
      "offset": 57239,
      "duration": 3101
    },
    {
      "text": "then a splotch of Overwatch, in their respective multiplayer modes with nostrils firmly clenched.",
      "offset": 60340,
      "duration": 3910
    },
    {
      "text": "This ran into the immediate stumbling block that Battleborn's servers are as lively as",
      "offset": 64250,
      "duration": 2990
    },
    {
      "text": "a swinger's sex party in the hip replacement ward.",
      "offset": 67240,
      "duration": 2010
    },
    {
      "text": "Yes, if there were hopes for a Coke and Pepsi style rivalry between the games they seem",
      "offset": 69250,
      "duration": 3360
    },
    {
      "text": "to have been well and truly dashed, the loser already poured down the sink to provide sewer",
      "offset": 72610,
      "duration": 3560
    },
    {
      "text": "rats with slightly claggy aftertaste for evermore.",
      "offset": 76170,
      "duration": 2339
    },
    {
      "text": "But people seemed to be down on Battleborn from the moment it came out, and I'm not sure",
      "offset": 78509,
      "duration": 3181
    },
    {
      "text": "I understand why.",
      "offset": 81690,
      "duration": 1000
    },
    {
      "text": "I mean yes, the gameplay's utterly boring and the menus are horribly designed and the",
      "offset": 82690,
      "duration": 3179
    },
    {
      "text": "dialogue writer's idea of creating personality is to make every character talk like Buffy",
      "offset": 85869,
      "duration": 3471
    },
    {
      "text": "the fucking Vampire Slayer, but in other words it's an entirely typical Gearbox game.",
      "offset": 89340,
      "duration": 3870
    },
    {
      "text": "I thought the same things of Borderlands and I seem to be the only person in the world",
      "offset": 93210,
      "duration": 3170
    },
    {
      "text": "who didn't like that bollocks.",
      "offset": 96380,
      "duration": 1099
    },
    {
      "text": "No, the fact is Overwatch has had media coverage that would bring envious tears to the corpse",
      "offset": 97479,
      "duration": 4041
    },
    {
      "text": "of Princess Diana and a doctrine has come down from the United Nations demanding everybody",
      "offset": 101520,
      "duration": 3770
    },
    {
      "text": "like it or have sanctions placed on their international trading, so Battleborn was pre-emptively",
      "offset": 105290,
      "duration": 3669
    },
    {
      "text": "dismissed as a cash-in imitator to be considered alongside Chinese bootlegs of superhero action",
      "offset": 108959,
      "duration": 4390
    },
    {
      "text": "figures named things like Spoderman and Batfellow.",
      "offset": 113349,
      "duration": 1981
    },
    {
      "text": "Which I don't think is fair.",
      "offset": 115330,
      "duration": 2120
    },
    {
      "text": "Yes, both games sell themselves on a big roster of colourful playable characters but then",
      "offset": 117450,
      "duration": 3130
    },
    {
      "text": "fighting games have been doing that for as long as my parents have stopped having sex.",
      "offset": 120580,
      "duration": 3250
    },
    {
      "text": "They are both first person shooters, but otherwise the experience is quite different.",
      "offset": 123830,
      "duration": 3659
    },
    {
      "text": "Battleborn allows single player, significantly, although the maps are expansive and every",
      "offset": 127489,
      "duration": 2951
    },
    {
      "text": "NPC with dialogue refers to you with plural pronouns so it does have a bit of that slightly",
      "offset": 130440,
      "duration": 3769
    },
    {
      "text": "depressing air of going to a theme park by yourself.",
      "offset": 134209,
      "duration": 2611
    },
    {
      "text": "Overwatch meanwhile has team-v-team multiplayer and that's it, and while I can respect wanting",
      "offset": 136820,
      "duration": 3949
    },
    {
      "text": "to focus on doing one thing really well rather than everything blandly, I'm iffy about selling",
      "offset": 140769,
      "duration": 4271
    },
    {
      "text": "such a game for full price.",
      "offset": 145040,
      "duration": 1559
    },
    {
      "text": "Its mentor Team Fortress 2 never cost seventy fucking bucks even before it was free, and",
      "offset": 146599,
      "duration": 4331
    },
    {
      "text": "Overwatch has micropayment sales on top of that.",
      "offset": 150930,
      "duration": 2199
    },
    {
      "text": "Blizzard must rack up a lot of maintenance costs polishing up those MASSIVE BRASS BALLS",
      "offset": 153129,
      "duration": 4000
    },
    {
      "text": "of theirs.",
      "offset": 157129,
      "duration": 1000
    },
    {
      "text": "I miss the days when video games were a thing that you bought and then owned, rather than",
      "offset": 158129,
      "duration": 3220
    },
    {
      "text": "something you are temporarily permitted to occupy in return for tithes and devotion,",
      "offset": 161349,
      "duration": 4060
    },
    {
      "text": "as you pray that your meagre offerings please the gods and stave off the inevitable Coming",
      "offset": 165409,
      "duration": 3800
    },
    {
      "text": "of the Great Server Shutdown.",
      "offset": 169209,
      "duration": 2161
    },
    {
      "text": "Battleborn has a series of campaign missions to go through in turn and only unlocks a handful",
      "offset": 171370,
      "duration": 3020
    },
    {
      "text": "of its characters at the start, while Overwatch splatters all its content and gameplay at",
      "offset": 174390,
      "duration": 3400
    },
    {
      "text": "you in one go.",
      "offset": 177790,
      "duration": 1020
    },
    {
      "text": "Overwatch strips naked in the doorway and goes for you like a jumping spider, Battleborn",
      "offset": 178810,
      "duration": 3171
    },
    {
      "text": "totters into the lounge wearing seventeen sweaters.",
      "offset": 181981,
      "duration": 2018
    },
    {
      "text": "I liked that Overwatch gave me a practice range where I could play each character in",
      "offset": 183999,
      "duration": 3070
    },
    {
      "text": "turn and figure out which one I liked the feel of, where all I could do at the outset",
      "offset": 187069,
      "duration": 2861
    },
    {
      "text": "of Battleborn was start a story mission, arbitrarily pick someone and hope that they're not one",
      "offset": 189930,
      "duration": 3589
    },
    {
      "text": "of the ones that needs other players around to push their wheelchair.",
      "offset": 193519,
      "duration": 2450
    },
    {
      "text": "The gameplay has a Mumorpugery feel in that the missions all feel like I'm doing an instance",
      "offset": 195969,
      "duration": 3201
    },
    {
      "text": "in World of Warcraft: streams of identical mobs broken up by the occasional miniboss",
      "offset": 199170,
      "duration": 3569
    },
    {
      "text": "and environments with really unfeasibly big furniture.",
      "offset": 202739,
      "duration": 2560
    },
    {
      "text": "Plus a lot of special attacks that boil down to 'hurt enemy', 'hurt enemy slightly more',",
      "offset": 205299,
      "duration": 3851
    },
    {
      "text": "and 'hurt several enemies who didn't figure out not to stand in the conspicuous glowing",
      "offset": 209150,
      "duration": 3220
    },
    {
      "text": "circle'.",
      "offset": 212370,
      "duration": 1000
    },
    {
      "text": "Each character in Overwatch meanwhile has three or four refined skills that all go toward",
      "offset": 213370,
      "duration": 2830
    },
    {
      "text": "making them good at one specific thing, so all the characters have to be unlocked from",
      "offset": 216200,
      "duration": 3160
    },
    {
      "text": "the start because otherwise it'd be like having to unlock one of the wheels on your car.",
      "offset": 219360,
      "duration": 3689
    },
    {
      "text": "In summary the difference is that Battleborn is a game of unlocking stuff and Overwatch",
      "offset": 223049,
      "duration": 3241
    },
    {
      "text": "isn't.",
      "offset": 226290,
      "duration": 1000
    },
    {
      "text": "You unlock characters, you unlock their skills and their skills reset every mission so you",
      "offset": 227290,
      "duration": 2710
    },
    {
      "text": "can have all the fun of unlocking them again.",
      "offset": 230000,
      "duration": 1499
    },
    {
      "text": "Maybe the way one character delivers their annoying quips endears them to you enough",
      "offset": 231499,
      "duration": 3140
    },
    {
      "text": "that you might want to unlock their backstory by completing various grind challenges, which",
      "offset": 234639,
      "duration": 3301
    },
    {
      "text": "seems like a pretty good way to make them less endearing really fucking fast.",
      "offset": 237940,
      "duration": 3280
    },
    {
      "text": "Overwatch only has cosmetic unlocks, and the system for that is frankly insulting.",
      "offset": 241220,
      "duration": 3790
    },
    {
      "text": "I play round after round, murder legions of my fellow man, woman and monkey cyborg, and",
      "offset": 245010,
      "duration": 3610
    },
    {
      "text": "for my efforts I'm awarded one loot box containing two banana stickers and a pink leotard for",
      "offset": 248620,
      "duration": 4349
    },
    {
      "text": "a character I hate.",
      "offset": 252969,
      "duration": 1000
    },
    {
      "text": "Mind you, I got more use out of those banana stickers putting them around the spawn waiting",
      "offset": 253969,
      "duration": 2821
    },
    {
      "text": "for the round to start than I did out of the gear I was unlocking in Battleborn, which",
      "offset": 256790,
      "duration": 3121
    },
    {
      "text": "promised to temporarily shave .7 seconds off my ball-scratching time if I could ever figure",
      "offset": 259911,
      "duration": 3699
    },
    {
      "text": "out how to equip the fucking things.",
      "offset": 263610,
      "duration": 1600
    },
    {
      "text": "I think it's safe to say that in the gameplay event Overwatch takes the trophy and covers",
      "offset": 265210,
      "duration": 3330
    },
    {
      "text": "it in banana stickers before Battleborn can even unlock its running shoes.",
      "offset": 268540,
      "duration": 3270
    },
    {
      "text": "But Battleborn has a plot, where Overwatch just has a paragraph on a website talking",
      "offset": 271810,
      "duration": 3410
    },
    {
      "text": "some guff about a robot invasion, giving bugger all explanation for why these dudes are arbitrarily",
      "offset": 275220,
      "duration": 4060
    },
    {
      "text": "teaming up to fight clones of each other.",
      "offset": 279280,
      "duration": 1690
    },
    {
      "text": "Remember that little controversy when Blizzard cut out a pose of a character sticking her",
      "offset": 280970,
      "duration": 3310
    },
    {
      "text": "bum out because one person complained?",
      "offset": 284280,
      "duration": 1640
    },
    {
      "text": "That annoyed me, not because of my personal bum preferences but because making a change",
      "offset": 285920,
      "duration": 3550
    },
    {
      "text": "after one solitary complaint shows just how little shit they gave about artistic vision.",
      "offset": 289470,
      "duration": 4190
    },
    {
      "text": "Every character is an archetype cynically designed to pander to some section of the",
      "offset": 293660,
      "duration": 3410
    },
    {
      "text": "audience.",
      "offset": 297070,
      "duration": 1000
    },
    {
      "text": "There's the obvious eye candy girlies wearing cling film but there's also a muscle lady",
      "offset": 298070,
      "duration": 3090
    },
    {
      "text": "and a chubby girl in specs so the genderspecials don't throw a strop.",
      "offset": 301160,
      "duration": 3120
    },
    {
      "text": "Then we'll have two samurais and a mecha girl for the weeaboos, a cowboy for dudes with",
      "offset": 304280,
      "duration": 3500
    },
    {
      "text": "slightly weird ideas about the masculine ideal and a skull face murderer for dudes with even",
      "offset": 307780,
      "duration": 3790
    },
    {
      "text": "weirder ideas about the masculine ideal.",
      "offset": 311570,
      "duration": 1770
    },
    {
      "text": "In contrast Battleborn's cast is scrappier but consequently comes across as more human",
      "offset": 313340,
      "duration": 3510
    },
    {
      "text": "and less focus grouped up the cling-film-covered arse.",
      "offset": 316850,
      "duration": 2160
    },
    {
      "text": "But at the end of the day you can't argue with fun, and Overwatch is plainly and simply",
      "offset": 319010,
      "duration": 3740
    },
    {
      "text": "more fun than Bloodbo - oop!",
      "offset": 322750,
      "duration": 1950
    },
    {
      "text": "Almost did it there, didn't I. I meant BATTLEBORN isn't as fun as Hovercrotch.",
      "offset": 324700,
      "duration": 3900
    },
    {
      "text": "Erm.",
      "offset": 328600,
      "duration": 1000
    },
    {
      "text": "Overpriced.",
      "offset": 329600,
      "duration": 90
    }
  ],
  "fetchedAt": "2025-12-14T10:35:55.862Z",
  "publishedAt": "2016-06-22"
}