{
  "video": {
    "id": "XSuqCI8VFWE",
    "title": "TOM CLANCY'S H.A.W.X. (Zero Punctuation)",
    "url": "https://youtu.be/XSuqCI8VFWE",
    "duration": 292,
    "playlistId": "unknown",
    "playlistTitle": "Zero Punctuation"
  },
  "captions": [
    {
      "text": "You've got to feel sorry for the American entertainment industry. The country comes home from a few decent world wars with a new image for itself as the glorious conquering heroes, and ever since then their existence has been one long quest for another worthy opponent.",
      "offset": 0,
      "duration": 26.6
    },
    {
      "text": "They're like Red Sonja minus the whole sex obligation as much as that would liven up global politics.",
      "offset": 26.6,
      "duration": 4.139999999999997
    },
    {
      "text": "They had a good thing going with the Russians for a while before East Berlin paid the price for shoddy building contractors",
      "offset": 30.74,
      "duration": 4.0000000000000036
    },
    {
      "text": "and in all their other wars it's difficult to root for America when the villains of the story live in a ditch and are armed with jagged rocks.",
      "offset": 34.74,
      "duration": 5.259999999999998
    },
    {
      "text": "At some point in recent years they looked up from their international heroism to realise they'd alienated the entire world",
      "offset": 40,
      "duration": 4.5
    },
    {
      "text": "and contemporary war stories now all seem to deftly avoid clearly associating the villains with a foreign power.",
      "offset": 44.5,
      "duration": 4.5
    },
    {
      "text": "It's quite entertaining to watch really, like how they used to put bears on hot plates to make them dance.",
      "offset": 49,
      "duration": 3.8400000000000034
    },
    {
      "text": "Tom Clancy's Hawks by Tom Clancy is another of my ventures into the gaming wilderness",
      "offset": 52.84,
      "duration": 3.319999999999993
    },
    {
      "text": "Subtitles by the Amara.org community",
      "offset": 56.16,
      "duration": 3
    },
    {
      "text": "Subtitles by the Amara.org community",
      "offset": 67.951294,
      "duration": 3
    },
    {
      "text": "I'm a tier elite too, and Hawks doesn't give you the option to autopilot everywhere to the tune of Hall of the Mountain King.",
      "offset": 97.951294,
      "duration": 4.240005999999994
    },
    {
      "text": "But I'm honestly surprised by how much I enjoyed Hawks.",
      "offset": 102.1913,
      "duration": 2.319990000000004
    },
    {
      "text": "After a fairly brief adjustment period in which I learned to complete a low-flying bombing run without getting my nose cone stuck in somebody's chimney,",
      "offset": 104.51129,
      "duration": 5.280000000000001
    },
    {
      "text": "I found the flying controls to be fairly intuitive and was soon gaily tearing up the skies, enjoying the lovely scenery served hot from Google Maps.",
      "offset": 109.79129,
      "duration": 5.759999999999991
    },
    {
      "text": "There's something like 20 different planes you can fly, but that's really just a bone for the enthusiasts.",
      "offset": 115.55129,
      "duration": 3.5200000000000102
    },
    {
      "text": "The only appreciable differences are the exact design of the expensive military arse you have to stare at all day,",
      "offset": 119.07129,
      "duration": 4.560003999999992
    },
    {
      "text": "And possibly a slight promotion from ludicrously fast to,",
      "offset": 123.631294,
      "duration": 2.5999960000000044
    },
    {
      "text": "there is a mosquito-shaped hole in my teeth.",
      "offset": 126.23129,
      "duration": 2.1200000000000045
    },
    {
      "text": "Combat technology really has gotten pretty foolproof in 2014,",
      "offset": 128.35129,
      "duration": 2.719999999999999
    },
    {
      "text": "makes me wonder why they even bother with pilots.",
      "offset": 131.07129,
      "duration": 1.8400000000000034
    },
    {
      "text": "For the ground-based and slow-moving targets, the computer does all the targeting for you.",
      "offset": 132.91129,
      "duration": 3.200009999999992
    },
    {
      "text": "All you have to do is press the fire button as soon as you're in range,",
      "offset": 136.1113,
      "duration": 2.239990000000006
    },
    {
      "text": "turning a large percentage of combat into a sequence of glorified quick events but the subtraction of fiddly gunning mechanics does allow one to concentrate on strategy In theory anyway for all the box boasts the only orders you can give to your wingmen are defend and attack I seen light switches with more tactics Subtitles by the Amara community",
      "offset": 138.35129,
      "duration": 5.551299999999998
    },
    {
      "text": "So you're taught how to disable the safeties and go into a whole different viewpoint.",
      "offset": 170.90259,
      "duration": 2.799999999999983
    },
    {
      "text": "It takes a bit of getting used to, in fact on the training level the unmanned drones shot me down three times,",
      "offset": 173.70259,
      "duration": 3.8999900000000025
    },
    {
      "text": "which was a little emasculating, but once I got the hang of it, all the dodging and pursuing was actually quite fun and effective.",
      "offset": 177.60258,
      "duration": 4.5
    },
    {
      "text": "So overall, I enjoyed Hawks. In fact, I might go as far to say that Hawks could well have sold me on air combat games.",
      "offset": 182.10258,
      "duration": 5
    },
    {
      "text": "But that's not funny, so let's find more things to rip on. The story's a nice fat target.",
      "offset": 187.10258,
      "duration": 3
    },
    {
      "text": "I wonder how much input Tom Clancy actually has on all the games that wear his name.",
      "offset": 190.10258,
      "duration": 3
    },
    {
      "text": "If it's a lot, he must be working pretty fucking flat out.",
      "offset": 193.10258,
      "duration": 2.5
    },
    {
      "text": "I doubt he'd have time to sleep or salute the American flag that required six times a day.",
      "offset": 195.60258,
      "duration": 3.5
    },
    {
      "text": "I'm going to give away some spoilers here, so if you're that bothered, stick your head in a bucket till the generic metal starts up.",
      "offset": 199.10258,
      "duration": 4.540019999999998
    },
    {
      "text": "Because the actual standing army of a foreign nation would have inconvenient things like patriotism and families and adorable pet doggies and shit,",
      "offset": 203.6426,
      "duration": 6.0800000000000125
    },
    {
      "text": "the bad guys of Hawks turn out to be private military contractors, the true bogeymen of our time.",
      "offset": 209.7226,
      "duration": 3.8599800000000073
    },
    {
      "text": "You start off working for them because the US Air Force their rights to stop them doing that",
      "offset": 213.58258,
      "duration": 22.831320000000005
    },
    {
      "text": "Who the hell's running this company?",
      "offset": 236.4139,
      "duration": 1.4799899999999866
    },
    {
      "text": "Scaramanga?",
      "offset": 237.89389,
      "duration": 1
    },
    {
      "text": "Why would a PMC invade the US?",
      "offset": 238.89389,
      "duration": 1.8400100000000066
    },
    {
      "text": "What were they going to do after killing the president?",
      "offset": 240.7339,
      "duration": 1.9199999999999875
    },
    {
      "text": "Declare themselves king.",
      "offset": 242.6539,
      "duration": 1.3199900000000184
    },
    {
      "text": "And where were they hiding all the soldiers and Hardware you'd need to wage war on a global superpower?",
      "offset": 243.97389,
      "duration": 4.080009999999987
    },
    {
      "text": "The fucking moon?",
      "offset": 248.0539,
      "duration": 1.3199999999999932
    },
    {
      "text": "I know that drama demands that the enemy actually be a plausible threat,",
      "offset": 249.3739,
      "duration": 2.680000000000007
    },
    {
      "text": "but I still think it'd have been more credible if the villains had been an army of disgruntled insect people from the Earth's core.",
      "offset": 252.0539,
      "duration": 5.28000000000003
    },
    {
      "text": "Wearing silly hats.",
      "offset": 262.4939,
      "duration": 1.5600000000000023
    },
    {
      "text": "Thanks for watching.",
      "offset": 272.6539,
      "duration": 11.819999999999993
    }
  ],
  "fetchedAt": "2025-12-14T11:45:25.185Z"
}