{
  "video": {
    "id": "zikB6RCR4Js",
    "title": "Dungeons of Hinterberg | Fully Ramblomatic",
    "url": "https://youtu.be/zikB6RCR4Js",
    "duration": 375,
    "playlistId": "PLUBKwq0XD0ueR3CXGUhGpsD1puLcYJPUp",
    "playlistTitle": "Second Wind"
  },
  "captions": [
    {
      "text": "Second Wind",
      "offset": 0.001,
      "duration": 4.416
    },
    {
      "text": "[Intro Music]",
      "offset": 4.417,
      "duration": 11.183
    },
    {
      "text": "Let&amp;#39;s take a moment to appreciate \nall the wonderful things that have  ",
      "offset": 15.6,
      "duration": 2.2
    },
    {
      "text": "come out of Austria. Don&amp;#39;t say Hitler, \nYahtz. Oh fine. Arnold Schwarzeneggar,  ",
      "offset": 17.8,
      "duration": 3.4
    },
    {
      "text": "there&amp;#39;s a good one. Erm. I hear the wine&amp;#39;s good, \nand mostly not poisoned now. And presumably a lot  ",
      "offset": 21.2,
      "duration": 5.04
    },
    {
      "text": "of people come from there who aren&amp;#39;t Hitler. Some \nof whom recently put out a nice little indie game  ",
      "offset": 26.24,
      "duration": 3.76
    },
    {
      "text": "called Dungeons of Hitler- I mean Hinterburg, \nwhich I want to talk about because, shockingly,  ",
      "offset": 30,
      "duration": 3.36
    },
    {
      "text": "I rather enjoyed it. In that nice genuine way \nwhere you wake up in the morning thinking &amp;quot;Ah,  ",
      "offset": 33.36,
      "duration": 3.64
    },
    {
      "text": "I&amp;#39;m looking forward to playing more of that \ngame today,&amp;quot; as opposed to the usual &amp;quot;Oh boy  ",
      "offset": 37,
      "duration": 3.44
    },
    {
      "text": "more grinding away in the dogshit mines \nfor the amusement of the cretins as soon  ",
      "offset": 40.44,
      "duration": 2.88
    },
    {
      "text": "as I half-heartedly rouse myself with a token \nsemi-erect wank like a car wash attendant shaking  ",
      "offset": 43.32,
      "duration": 4.04
    },
    {
      "text": "the foam off a pink chamois leather.&amp;quot; Dungeons \nof Very Austrian Sounding Name follows Luisa,  ",
      "offset": 47.36,
      "duration": 4.32
    },
    {
      "text": "a lawyer from Vienna who takes a holiday in one \nof Austria&amp;#39;s lovely picturesque mountain villages,  ",
      "offset": 51.68,
      "duration": 4.08
    },
    {
      "text": "where she has a very authentic European \npackage tour experience: getting dragged  ",
      "offset": 55.76,
      "duration": 3.16
    },
    {
      "text": "out of bed at 7am every morning to get herded to \nsome local heritage site, where gangs of locals  ",
      "offset": 58.92,
      "duration": 3.8
    },
    {
      "text": "in spooky masks try to hit her with sticks. Or \nmaybe that was just my last trip to Stockholm.",
      "offset": 62.72,
      "duration": 4.16
    },
    {
      "text": "In this age where the spectre of coziness hangs \nover indie gaming like a great big magenta  ",
      "offset": 66.88,
      "duration": 3.68
    },
    {
      "text": "Hindenburg there have been many games that have \ntried to bridge the gap between cozy gaming and  ",
      "offset": 70.56,
      "duration": 3.88
    },
    {
      "text": "traditional action stuff, usually ending up in \nsome unsatisfying inbetween space where zombies  ",
      "offset": 74.44,
      "duration": 4.32
    },
    {
      "text": "keep nibbling your bum while you&amp;#39;re trying \nto water the carrots. But I think Dungeons of  ",
      "offset": 78.76,
      "duration": 3.2
    },
    {
      "text": "Hindenburg successfully straddles that particular \nsex swing. The secret sauce is that your time is  ",
      "offset": 81.96,
      "duration": 4.2
    },
    {
      "text": "strictly regimented in a very characteristically \nGermanic kind of way, or more informatively  ",
      "offset": 86.16,
      "duration": 4
    },
    {
      "text": "a very Persona-y kind of way. Your time is divided \ninto slots, in the morning you pick an adventuring  ",
      "offset": 90.16,
      "duration": 4.04
    },
    {
      "text": "area you want to explore looking for dungeons \nto complete and goblins to bully with sticks,  ",
      "offset": 94.2,
      "duration": 3.56
    },
    {
      "text": "and then in the afternoon slot you hang around \ntown shopping and hanging out with your pals,  ",
      "offset": 97.76,
      "duration": 3.24
    },
    {
      "text": "building up relationship scores and your \nsocial stats in order to improve your  ",
      "offset": 101,
      "duration": 2.84
    },
    {
      "text": "ability to bully goblins with sticks. It&amp;#39;s \nthat same Persona dual gameplay model where  ",
      "offset": 103.84,
      "duration": 3.6
    },
    {
      "text": "the two modes are separated but affect \neach other, like a bathroom glory hole  ",
      "offset": 107.44,
      "duration": 3.32
    },
    {
      "text": "situation with another larger hole to \nthe side to accommodate reach-arounds.",
      "offset": 110.76,
      "duration": 3.2
    },
    {
      "text": "So in summary it&amp;#39;s very much like Persona \nexcept with real-time instead of turn-based  ",
      "offset": 113.96,
      "duration": 3.32
    },
    {
      "text": "combat. Slightly janky and repetitive real-time \ncombat, and I&amp;#39;m not a huge fan of the visual  ",
      "offset": 117.28,
      "duration": 3.88
    },
    {
      "text": "style because every character&amp;#39;s got this thing \ngoing on with their upper lip that makes it look  ",
      "offset": 121.16,
      "duration": 2.96
    },
    {
      "text": "like they&amp;#39;ve all got Poirot moustaches. So I \nhave more than a few red marks on Funyuns of  ",
      "offset": 124.12,
      "duration": 3.76
    },
    {
      "text": "Heisenberg&amp;#39;s balance sheet, but if there&amp;#39;s \none aspect of it I like above all else,  ",
      "offset": 127.88,
      "duration": 3.12
    },
    {
      "text": "it&amp;#39;s the premise. A bunch of magic portals appear \nin the country surrounding an Austrian village,  ",
      "offset": 131,
      "duration": 3.92
    },
    {
      "text": "out of which goblins and goblin-adjacent \nmonsters start spilling and attacking the locals,  ",
      "offset": 134.92,
      "duration": 3.84
    },
    {
      "text": "and each one leads to a strange ethereal \ndungeon full of trials of combat prowess  ",
      "offset": 138.76,
      "duration": 3.04
    },
    {
      "text": "and puzzle-solving intellect. But instead of \ndoing the normal, sensible thing that peasant  ",
      "offset": 141.8,
      "duration": 2.92
    },
    {
      "text": "villages do when these things happen, i.e. enlist \na wandering hero to save them from the monsters,  ",
      "offset": 144.72,
      "duration": 3.92
    },
    {
      "text": "the peasants of Hinterburg instead hit upon \nthe idea of letting tourists into the dungeons,  ",
      "offset": 148.64,
      "duration": 3.64
    },
    {
      "text": "and now its entire economy is based around selling \npotions and swords and all the dungeon portals  ",
      "offset": 152.28,
      "duration": 4.08
    },
    {
      "text": "have wheelchair ramps and difficulty ratings \non signs like they&amp;#39;re fucking ski slopes.",
      "offset": 156.36,
      "duration": 3.52
    },
    {
      "text": "And I wonder why the villagers in \nDiablo never thought to do this,  ",
      "offset": 159.88,
      "duration": 2.48
    },
    {
      "text": "I mean, either the demons all get killed by \nadventurers or annoyed to death by influencers,  ",
      "offset": 162.36,
      "duration": 3.64
    },
    {
      "text": "it&amp;#39;s the most economically savvy move by an \nNPC since the potion brewer discovered high  ",
      "offset": 166,
      "duration": 3.48
    },
    {
      "text": "fructose corn syrup. The setting is remarkably \nwell-realised, thanks in part to the range of  ",
      "offset": 169.48,
      "duration": 3.68
    },
    {
      "text": "characters you meet and can become friends with \n- fellow adventurer tourists, the business-owning  ",
      "offset": 173.16,
      "duration": 3.48
    },
    {
      "text": "locals who appreciate being able to flog \noverpriced plush kobolds to dickheads, the more  ",
      "offset": 176.64,
      "duration": 3.72
    },
    {
      "text": "conservative locals who wish there weren&amp;#39;t so many \ndickheads around, and the hipsters complaining  ",
      "offset": 180.36,
      "duration": 3.44
    },
    {
      "text": "about how the commercialization and inauthenticity \nof the tourist experience is irritating the dick  ",
      "offset": 183.8,
      "duration": 4
    },
    {
      "text": "growing prominently out of their heads. There&amp;#39;s \na nice dual satire going on of both video game  ",
      "offset": 187.8,
      "duration": 4.04
    },
    {
      "text": "tropes and tourist trap destinations with a \nsubtle underlying environmental message but while  ",
      "offset": 191.84,
      "duration": 4.08
    },
    {
      "text": "treating a monster-stricken peasant village as a \nrelaxing getaway for city folk is the main gag,  ",
      "offset": 195.92,
      "duration": 4.44
    },
    {
      "text": "the really funny part is that it kinda is. \nRelaxing, I mean. You wake up in the morning,  ",
      "offset": 200.36,
      "duration": 4.04
    },
    {
      "text": "have breakfast on the veranda, choose a nice \nscenic environment to explore and then work  ",
      "offset": 204.4,
      "duration": 3.36
    },
    {
      "text": "out all those little workaday frustrations by \npunching a load of goblins in the face so hard  ",
      "offset": 207.76,
      "duration": 3.64
    },
    {
      "text": "that they&amp;#39;ll have to brush their teeth tomorrow \nby bum-shuffling across a shagpile carpet.",
      "offset": 211.4,
      "duration": 3.68
    },
    {
      "text": "Having said that, the combat&amp;#39;s nothing to write \nhome about on an erotic postcard. The dungeons are  ",
      "offset": 215.08,
      "duration": 3.8
    },
    {
      "text": "very Zelda-esque sequences of challenges themed \naround the bespoke magic spells available in each  ",
      "offset": 218.88,
      "duration": 3.6
    },
    {
      "text": "region, ranging from sequential lever pulling \npuzzles to snowboarding runs, and the combat is  ",
      "offset": 222.48,
      "duration": 3.96
    },
    {
      "text": "by far the least interesting part of any of it, \nyou enter a room and a fucking curtain comes down  ",
      "offset": 226.44,
      "duration": 3.76
    },
    {
      "text": "and a bunch of generic black monsters round on you \nfor no better reason than to gatekeep people who  ",
      "offset": 230.2,
      "duration": 3.8
    },
    {
      "text": "didn&amp;#39;t show up with high enough level gear like \na bunch of weird-smelling thirty year old men  ",
      "offset": 234,
      "duration": 3.28
    },
    {
      "text": "loitering in the hallway outside a wargaming shop. \nYour combat abilities are provided by the usual  ",
      "offset": 237.28,
      "duration": 4
    },
    {
      "text": "law firm, Attack, Parry, and Dodge associates, \nbut it&amp;#39;s barely worth putting the effort in to  ",
      "offset": 241.28,
      "duration": 4
    },
    {
      "text": "master it when you&amp;#39;ve also got overpowered super \nattacks and magic attacks, all of which feels like  ",
      "offset": 245.28,
      "duration": 3.88
    },
    {
      "text": "overkill when you exclusively use it against \nthe same ambulatory blobs of Marmite-flavoured  ",
      "offset": 249.16,
      "duration": 4.12
    },
    {
      "text": "play-doh as always. Only each area&amp;#39;s token boss \nfight is interesting, and in the grand Zelda  ",
      "offset": 253.28,
      "duration": 4.44
    },
    {
      "text": "tradition these are more puzzle challenges \nabout deducing the correct spells to use. \n  ",
      "offset": 257.72,
      "duration": 3.56
    },
    {
      "text": "And even then the fights don&amp;#39;t evolve at all. The \nbig butterfly lady just keeps blithely descending  ",
      "offset": 261.28,
      "duration": 4.2
    },
    {
      "text": "into range, never ceasing to be surprised when we \nmatter-of-factly pull one of her wings off with  ",
      "offset": 265.48,
      "duration": 3.56
    },
    {
      "text": "our grapple beam for the fourth time. The nicest \nthing one can say about the combat is that it&amp;#39;s  ",
      "offset": 269.04,
      "duration": 3.72
    },
    {
      "text": "functional enough for purpose, which is to be \nthe thing that you do when you&amp;#39;re not doing the  ",
      "offset": 272.76,
      "duration": 3.88
    },
    {
      "text": "other thing. You don&amp;#39;t actually have to go into \na dungeon every day, you can opt to hang out at  ",
      "offset": 276.64,
      "duration": 3.72
    },
    {
      "text": "a beauty spot to increment your Relaxation \nstat, although that&amp;#39;s a very un-relaxing way  ",
      "offset": 280.36,
      "duration": 3.8
    },
    {
      "text": "of putting it. And by upping our social stats \nwe acquire more opportunities to make friends  ",
      "offset": 284.16,
      "duration": 3.96
    },
    {
      "text": "and gain the buffs that make the combat less \nof a pain in the Hintern. But the necessity  ",
      "offset": 288.12,
      "duration": 3.72
    },
    {
      "text": "of all that is questionable. I assumed my goal \nwas just to beat the dungeons and was slightly  ",
      "offset": 291.84,
      "duration": 3.92
    },
    {
      "text": "put out at the end when there were multiple NPCs \nand activities I never needed to interact with  ",
      "offset": 295.76,
      "duration": 4.08
    },
    {
      "text": "at all. The game&amp;#39;s a lot better if instead \nyou assume your goal is to make friends with  ",
      "offset": 299.84,
      "duration": 3.8
    },
    {
      "text": "everyone and play out their stories. Which does \nsmack of making excuses. It&amp;#39;s like saying the  ",
      "offset": 303.64,
      "duration": 3.88
    },
    {
      "text": "combat actually becomes quite interesting if \nyou do it with both index fingers stuck up a  ",
      "offset": 307.52,
      "duration": 3.52
    },
    {
      "text": "dog&amp;#39;s arse. I shouldn&amp;#39;t have to do that, is the \npoint. And the dogs weren&amp;#39;t thrilled, either.",
      "offset": 311.04,
      "duration": 4.294
    }
  ],
  "fetchedAt": "2025-12-14T10:57:49.509Z"
}